py_sciplot-0.1.1.dist-info/METADATA
py_sciplot-0.1.1.dist-info/RECORD
py_sciplot-0.1.1.dist-info/WHEEL
py_sciplot-0.1.1.dist-info/top_level.txt
sciplot/__init__.py
sciplot/analysis.py
sciplot/colors.py
sciplot/decorations.py
sciplot/functions.py
sciplot/helpers.py
sciplot/skeleton.py
