Metadata-Version: 2.1
Name: py-sciplot
Version: 0.1.1
Summary: Add a short description here!
Home-page: https://github.com/simonUU/sciplot
Author: Simon Wehle
Author-email: simon.wehle@desy.de
License: mit
Platform: any
Classifier: Development Status :: 4 - Beta
Classifier: Programming Language :: Python
Provides-Extra: testing
Provides-Extra: testing
Requires-Dist: pytest; extra == 'testing'
Requires-Dist: pytest-cov; extra == 'testing'
